lyricalabs/__init__.py
lyricalabs/nexaclient.py
lyricalabs-0.1.2.dist-info/licenses/LICENSE
lyricalabs-0.1.2.dist-info/METADATA
lyricalabs-0.1.2.dist-info/WHEEL
lyricalabs-0.1.2.dist-info/top_level.txt
lyricalabs-0.1.2.dist-info/RECORD
