Metadata-Version: 2.4
Name: lyricalabs
Version: 0.1.2
Summary: Lyrica Labs API Python, Nexa LLM
Home-page: https://lyricalabs.vercel.app
Author: Lyrica Labs
Author-email: lyricalabs@gmail.com
Classifier: Programming Language :: Python :: 3
Classifier: Operating System :: OS Independent
Requires-Python: >=3.8
License-File: LICENSE
Requires-Dist: requests
Dynamic: author
Dynamic: author-email
Dynamic: classifier
Dynamic: description
Dynamic: description-content-type
Dynamic: home-page
Dynamic: license-file
Dynamic: requires-dist
Dynamic: requires-python
Dynamic: summary
